file2code/cli.py
file2code/core.py
file2code/init.py
file2code-1.0.0.dist-info/METADATA
file2code-1.0.0.dist-info/WHEEL
file2code-1.0.0.dist-info/entry_points.txt
file2code-1.0.0.dist-info/top_level.txt
file2code-1.0.0.dist-info/RECORD
